{
    "analysis_version": 7,
    "android_app_support": false,
    "aue_date": "2021-06-02 00:00:00",
    "boards": [
        "tidus"
    ],
    "chromeos_auserver": "https://tools.google.com/service/update2",
    "chromeos_board_appid": "{4A52D805-8FA6-43A1-9F71-C1A59FD918E8}",
    "chromeos_canary_appid": "{90F229CE-83E2-4FAF-8479-E368A34938B1}",
    "chromeos_devserver": "",
    "chromeos_release_appid": "{4A52D805-8FA6-43A1-9F71-C1A59FD918E8}",
    "chromeos_release_board": "tidus-signed-mp-v2keys",
    "chromeos_release_branch_number": "45",
    "chromeos_release_build_number": "13729",
    "chromeos_release_build_type": "Official Build",
    "chromeos_release_builder_path": "tidus-release/R89-13729.45.0",
    "chromeos_release_chrome_milestone": "89",
    "chromeos_release_description": "13729.45.0 (Official Build) stable-channel tidus ",
    "chromeos_release_keyset": "mp-v2",
    "chromeos_release_name": "Chrome OS",
    "chromeos_release_patch_number": "0",
    "chromeos_release_track": "stable-channel",
    "chromeos_release_version": "13729.45.0",
    "cr_version": 89,
    "cros_version": 13729,
    "crostini_support": true,
    "devicetype": "CHROMEBOX",
    "file": "chromeos_13729.45.0_tidus_recovery_stable-channel_mp-v2.bin",
    "filesize": 2319657472,
    "google_release": "13729.45.0",
    "hwidmatches": [
        "^TIDUS .*"
    ],
    "image_name": "tidus",
    "linux_kernel_versions": [
        "4.14.214-17103-g887e64348b2b"
    ],
    "manufacturers": [
        "Lenovo"
    ],
    "md5": "37a5775f8ca4fd4d4bced893b2c2a2a1",
    "models": [
        "Lenovo ThinkCentre Chromebox"
    ],
    "names": [
        "Lenovo ThinkCentre Chromebox"
    ],
    "sample_hwid": "TIDUS NNN",
    "sha1": "10cd6a442a6cb62c783aff172696a4cde02d889d",
    "url": "https://dl.google.com/dl/edgedl/chromeos/recovery/chromeos_13729.45.0_tidus_recovery_stable-channel_mp-v2.bin.zip",
    "version": "13729.45.0",
    "zipfilesize": 680477175
}