{
    "analysis_version": 6,
    "android_app_support": true,
    "android_version": "Android Pie 9",
    "aue_date": "2026-06-02 00:00:00",
    "boards": [
        "leona",
        "rammus",
        "shyvana"
    ],
    "chromeos_arc_android_sdk_version": "28",
    "chromeos_arc_version": "5563074",
    "chromeos_auserver": "https://tools.google.com/service/update2",
    "chromeos_board_appid": "{625849FA-56A0-4E67-9163-B89BE0C2A6AE}",
    "chromeos_canary_appid": "{90F229CE-83E2-4FAF-8479-E368A34938B1}",
    "chromeos_devserver": "",
    "chromeos_release_appid": "{625849FA-56A0-4E67-9163-B89BE0C2A6AE}",
    "chromeos_release_board": "rammus-signed-mp-v2keys",
    "chromeos_release_branch_number": "118",
    "chromeos_release_build_number": "11895",
    "chromeos_release_build_type": "Official Build",
    "chromeos_release_builder_path": "rammus-release/R74-11895.118.0",
    "chromeos_release_chrome_milestone": "74",
    "chromeos_release_description": "11895.118.0 (Official Build) stable-channel rammus ",
    "chromeos_release_keyset": "mp-v2",
    "chromeos_release_name": "Chrome OS",
    "chromeos_release_patch_number": "0",
    "chromeos_release_track": "stable-channel",
    "chromeos_release_unibuild": "1",
    "chromeos_release_version": "11895.118.0",
    "cr_version": 74,
    "cros_version": 11895,
    "crostini_support": true,
    "devicetype": "CHROMEBOOK",
    "file": "chromeos_11895.118.0_rammus_recovery_stable-channel_mp-v2.bin",
    "google_release": "11895.118.0",
    "hwidmatches": [
        "^LEONA .*",
        "SHYVANA (...-){3}..[37]",
        "SHYVANA (...-){3}..[37]",
        "^SHYVANA .*"
    ],
    "image_name": "rammus",
    "linux_kernel_versions": [
        "4.4.176-16038-g1367a8f4b427"
    ],
    "manufacturers": [
        "Asus",
        "Asus",
        "Asus",
        "Asus"
    ],
    "md5": "8ae9a4213c58b1370d6a5a3331ed6213",
    "models": [
        "ASUS Chromebook C425",
        "ASUS Chromebook Flip C433",
        "ASUS Chromebook Flip C433",
        "ASUS Chromebook Flip C434"
    ],
    "names": [
        "ASUS Chromebook C425",
        "ASUS Chromebook Flip C433",
        "ASUS Chromebook Flip C433",
        "ASUS Chromebook Flip C434"
    ],
    "sha1": "70f6947819cd104b41e25c68df953be0f38437a9",
    "url": "https://dl.google.com/dl/edgedl/chromeos/recovery/chromeos_11895.118.0_rammus_recovery_stable-channel_mp-v2.bin.zip",
    "version": 11895
}