{
    "analysis_version": 8,
    "android_app_support": true,
    "android_version": "Android Pie 9",
    "aue_date": "2027-06-02 00:00:00",
    "boards": [
        "sand"
    ],
    "chromeos_arc_android_sdk_version": "28",
    "chromeos_arc_version": "11419986",
    "chromeos_auserver": "https://tools.google.com/service/update2",
    "chromeos_board_appid": "{533B7092-5828-48E6-9F77-C7ADCBF8F7E9}",
    "chromeos_canary_appid": "{90F229CE-83E2-4FAF-8479-E368A34938B1}",
    "chromeos_devserver": "",
    "chromeos_release_appid": "{533B7092-5828-48E6-9F77-C7ADCBF8F7E9}",
    "chromeos_release_board": "sand-signed-mp-v3keys",
    "chromeos_release_branch_number": "66",
    "chromeos_release_build_number": "15699",
    "chromeos_release_build_type": "Official Build",
    "chromeos_release_builder_path": "sand-release/R121-15699.66.0",
    "chromeos_release_chrome_milestone": "121",
    "chromeos_release_description": "15699.66.0 (Official Build) stable-channel sand ",
    "chromeos_release_keyset": "mp-v3",
    "chromeos_release_name": "Chrome OS",
    "chromeos_release_patch_number": "0",
    "chromeos_release_track": "stable-channel",
    "chromeos_release_unibuild": "1",
    "chromeos_release_version": "15699.66.0",
    "cr_version": 121,
    "cros_version": 15699,
    "crostini_support": true,
    "devicetype": "CHROMEBOOK",
    "file": "chromeos_15699.66.0_sand_recovery_stable-channel_mp-v3.bin",
    "filesize": 2331383808,
    "google_release": "15699.66.0",
    "hwidmatches": [
        "^SAND .*",
        "^SAND .*",
        "^SAND .*",
        "^SAND .*",
        "^SAND .*"
    ],
    "image_name": "sand",
    "is_chromebook_plus_device": false,
    "linux_kernel_versions": [
        "5.10.202-23728-g7568b763bd2c"
    ],
    "manufacturers": [
        "Acer",
        "Acer",
        "Acer",
        "Acer",
        "Acer"
    ],
    "md5": "c6b64028f9eb021d5cb01dc9ee7e2db5",
    "models": [
        "Acer Chromebook 15 (CB515-1H, CB515-1HT)",
        "Acer Chromebook 15 (CB515-1H, CB515-1HT)",
        "Acer Chromebook 15 (CB515-1H, CB515-1HT)",
        "Acer Chromebook 15 (CB515-1H, CB515-1HT)",
        "Acer Chromebook 15 (CB515-1H, CB515-1HT)"
    ],
    "names": [
        "Acer Chromebook 15 (CB515-1H, CB515-1HT)",
        "Acer Chromebook 15 (CB515-1H, CB515-1HT)",
        "Acer Chromebook 15 (CB515-1H, CB515-1HT)",
        "Acer Chromebook 15 (CB515-1H, CB515-1HT)",
        "Acer Chromebook 15 (CB515-1H, CB515-1HT)"
    ],
    "parallels_support": false,
    "sample_hwid": "SAND NNNN",
    "sha1": "bf74ffde507f68f393dafc6510ffa48daa4e7a0c",
    "url": "https://dl.google.com/dl/edgedl/chromeos/recovery/chromeos_15699.66.0_sand_recovery_stable-channel_mp-v3.bin.zip",
    "version": "15699.66.0",
    "zipfilesize": 1404478244
}