{
    "analysis_version": 7,
    "android_app_support": false,
    "aue_date": "2021-09-02 00:00:00",
    "boards": [
        "candy"
    ],
    "chromeos_auserver": "https://tools.google.com/service/update2",
    "chromeos_board_appid": "{BABC2E82-8F7D-26E5-EE66-4C60A2B41DBC}",
    "chromeos_canary_appid": "{90F229CE-83E2-4FAF-8479-E368A34938B1}",
    "chromeos_devserver": "",
    "chromeos_release_appid": "{BABC2E82-8F7D-26E5-EE66-4C60A2B41DBC}",
    "chromeos_release_board": "candy-signed-mp-v2keys",
    "chromeos_release_branch_number": "66",
    "chromeos_release_build_number": "12499",
    "chromeos_release_build_type": "Official Build",
    "chromeos_release_builder_path": "candy-release/R78-12499.66.0",
    "chromeos_release_chrome_milestone": "78",
    "chromeos_release_description": "12499.66.0 (Official Build) stable-channel candy ",
    "chromeos_release_keyset": "mp-v2",
    "chromeos_release_name": "Chrome OS",
    "chromeos_release_patch_number": "0",
    "chromeos_release_track": "stable-channel",
    "chromeos_release_version": "12499.66.0",
    "cr_version": 78,
    "cros_version": 12499,
    "crostini_support": false,
    "devicetype": "CHROMEBOOK",
    "file": "chromeos_12499.66.0_candy_recovery_stable-channel_mp-v2.bin",
    "google_release": "12499.66.0",
    "hwidmatches": [
        "^CANDY .*"
    ],
    "image_name": "candy",
    "linux_kernel_versions": [
        "4.4.190-16770-gb3c36ab5af98"
    ],
    "manufacturers": [
        "Dell"
    ],
    "md5": "e7f1f87b11f7e4910a83e17752e58f07",
    "models": [
        "Dell Chromebook 11 (3120)"
    ],
    "names": [
        "Dell Chromebook 11 (3120)"
    ],
    "sample_hwid": "CANDY NNN",
    "sha1": "a61a6821d45c46f21ce4566a129742f4e402c9e2",
    "url": "https://dl.google.com/dl/edgedl/chromeos/recovery/chromeos_12499.66.0_candy_recovery_stable-channel_mp-v2.bin.zip",
    "version": 12499
}