{
    "most_common": {
        "144": "16503.76.0",
        "145": "16552.59.0",
        "146": "16581.54.0",
        "147": "16610.52.0",
        "148": "16640.61.0",
        "149": "16667.55.0",
        "beta": "16700.32.0",
        "canary": "16739.0.0",
        "dev": "16718.0.0",
        "stable": "16667.55.0"
    },
    "newest": {
        "144": "16503.76.0",
        "145": "16552.59.0",
        "146": "16581.61.0",
        "147": "16610.57.0",
        "148": "16640.61.0",
        "149": "16667.55.0",
        "beta": "16700.32.0",
        "canary": "16739.0.0",
        "dev": "16718.0.0",
        "stable": "16667.55.0"
    }
}