{
    "analysis_version": 7,
    "android_app_support": true,
    "android_version": "Android Pie 9",
    "aue_date": "2023-08-02 00:00:00",
    "boards": [
        "druwl"
    ],
    "chromeos_arc_android_sdk_version": "28",
    "chromeos_arc_version": "8946162",
    "chromeos_auserver": "https://tools.google.com/service/update2",
    "chromeos_board_appid": "{F1C30EB2-8429-4A18-9321-93E224753A98}",
    "chromeos_canary_appid": "{90F229CE-83E2-4FAF-8479-E368A34938B1}",
    "chromeos_devserver": "",
    "chromeos_release_appid": "{F1C30EB2-8429-4A18-9321-93E224753A98}",
    "chromeos_release_board": "scarlet-signed-mp-v7keys",
    "chromeos_release_branch_number": "85",
    "chromeos_release_build_number": "14989",
    "chromeos_release_build_type": "Official Build",
    "chromeos_release_builder_path": "scarlet-release/R105-14989.85.0",
    "chromeos_release_chrome_milestone": "105",
    "chromeos_release_description": "14989.85.0 (Official Build) stable-channel scarlet ",
    "chromeos_release_keyset": "mp-v7",
    "chromeos_release_name": "Chrome OS",
    "chromeos_release_patch_number": "0",
    "chromeos_release_track": "stable-channel",
    "chromeos_release_unibuild": "1",
    "chromeos_release_version": "14989.85.0",
    "cr_version": 105,
    "cros_version": 14989,
    "crostini_support": true,
    "devicetype": "CHROMEBOOK",
    "file": "chromeos_14989.85.0_scarlet_recovery_stable-channel_mp-v7.bin",
    "filesize": 2337001984,
    "google_release": "14989.85.0",
    "hwidmatches": [
        "^DRUWL [A-Z0-9][A-Z0-9]B.*"
    ],
    "image_name": "scarlet",
    "linux_kernel_versions": [
        "5.10.131-19114-g6651b07c6153"
    ],
    "manufacturers": [
        "Quanta CL"
    ],
    "md5": "973a9888143285a341d4641548149c95",
    "models": [
        "Quanta CL druwl"
    ],
    "names": [
        "druwl"
    ],
    "parallels_support": false,
    "sample_hwid": "DRUWL 5FBNNN",
    "sha1": "bc409bd742282b14bff28dafd6d1042a7cb926d9",
    "url": "https://dl.google.com/dl/edgedl/chromeos/recovery/chromeos_14989.85.0_scarlet_recovery_stable-channel_mp-v7.bin.zip",
    "version": "14989.85.0",
    "zipfilesize": 1292709398
}