{
    "analysis_version": 7,
    "android_app_support": true,
    "android_version": "Android Pie 9",
    "aue_date": "2024-06-02 00:00:00",
    "boards": [
        "whitetip"
    ],
    "chromeos_arc_android_sdk_version": "28",
    "chromeos_arc_version": "10061634",
    "chromeos_auserver": "https://tools.google.com/service/update2",
    "chromeos_board_appid": "{5A3AB642-2A67-470A-8F37-37E737A53CFC}",
    "chromeos_canary_appid": "{90F229CE-83E2-4FAF-8479-E368A34938B1}",
    "chromeos_devserver": "",
    "chromeos_release_appid": "{5A3AB642-2A67-470A-8F37-37E737A53CFC}",
    "chromeos_release_board": "coral-signed-mp-v21keys",
    "chromeos_release_branch_number": "58",
    "chromeos_release_build_number": "15393",
    "chromeos_release_build_type": "Official Build",
    "chromeos_release_builder_path": "coral-release/R113-15393.58.0",
    "chromeos_release_chrome_milestone": "113",
    "chromeos_release_description": "15393.58.0 (Official Build) stable-channel coral ",
    "chromeos_release_keyset": "mp-v21",
    "chromeos_release_name": "Chrome OS",
    "chromeos_release_patch_number": "0",
    "chromeos_release_track": "stable-channel",
    "chromeos_release_unibuild": "1",
    "chromeos_release_version": "15393.58.0",
    "cr_version": 113,
    "cros_version": 15393,
    "crostini_support": true,
    "devicetype": "CHROMEBOOK",
    "file": "chromeos_15393.58.0_coral_recovery_stable-channel_mp-v21.bin",
    "filesize": 2330928640,
    "google_release": "15393.58.0",
    "hwidmatches": [
        "^WHITETIP DEVELOPMENT"
    ],
    "image_name": "coral",
    "linux_kernel_versions": [
        "5.10.175-22068-g4b67de084816"
    ],
    "manufacturers": [
        "Bitland CL"
    ],
    "md5": "8b0e19ab2e4b1dee4a643c617323372c",
    "models": [
        "Bitland CL whitetip"
    ],
    "names": [
        "whitetip"
    ],
    "parallels_support": false,
    "sample_hwid": "WHITETIP DEVELOPMENT",
    "sha1": "3715a35fba92c1fa4a21e28256450d7143cea7c1",
    "url": "https://dl.google.com/dl/edgedl/chromeos/recovery/chromeos_15393.58.0_coral_recovery_stable-channel_mp-v21.bin.zip",
    "version": "15393.58.0",
    "zipfilesize": 1399635714
}