{
    "analysis_version": 7,
    "android_app_support": false,
    "aue_date": "None",
    "boards": [
        "mario"
    ],
    "chromeos_auserver": "https://tools.google.com/service/update2",
    "chromeos_board_appid": "{87efface-864d-49a5-9bb3-4b050a7c227a}",
    "chromeos_canary_appid": "{90F229CE-83E2-4FAF-8479-E368A34938B1}",
    "chromeos_devserver": "",
    "chromeos_release_appid": "{87efface-864d-49a5-9bb3-4b050a7c227a}",
    "chromeos_release_board": "x86-mario-signed-mp-v3keys",
    "chromeos_release_branch_number": "91",
    "chromeos_release_build_number": "9000",
    "chromeos_release_build_type": "Official Build",
    "chromeos_release_builder_path": "x86-mario-release/R56-9000.91.0",
    "chromeos_release_chrome_milestone": "56",
    "chromeos_release_description": "9000.91.0 (Official Build) stable-channel x86-mario ",
    "chromeos_release_name": "Chrome OS",
    "chromeos_release_patch_number": "0",
    "chromeos_release_track": "stable-channel",
    "chromeos_release_version": "9000.91.0",
    "cr_version": 56,
    "cros_version": 9000,
    "crostini_support": false,
    "devicetype": "CHROMEBOOK",
    "file": "chromeos_9000.91.0_x86-mario_recovery_stable-channel_mario-mp-v3.bin",
    "filesize": 1535082496,
    "google_release": "9000.91.0",
    "hwidmatches": [
        "^IEC MARIO .*"
    ],
    "image_name": "mario",
    "linux_kernel_versions": [
        "3.8.11"
    ],
    "manufacturers": [
        "Google"
    ],
    "md5": "fb07ae3e8a60358b8d75e2d723a8ba81",
    "models": [
        "Google Cr-48"
    ],
    "names": [
        "Google Cr-48"
    ],
    "sample_hwid": "IEC MARIO NNN",
    "sha1": "c4143c96d3b2915ca8d787daafdaf957c65f8b0f",
    "url": "https://dl.google.com/dl/edgedl/chromeos/recovery/chromeos_9000.91.0_x86-mario_recovery_stable-channel_mario-mp-v3.bin.zip",
    "version": "9000.91.0",
    "zipfilesize": 589514617
}