{
    "boards": [
        "damu",
        "cozmo",
        "willow",
        "kenzo",
        "juniper",
        "pico",
        "esche",
        "kappa",
        "burnet",
        "fennel14",
        "fennel",
        "makomo"
    ],
    "cr_version": 115,
    "cros_version": 15474,
    "file": "chromeos_15474.84.0_jacuzzi_recovery_stable-channel_mp-v13.bin",
    "filesize": 4962900480,
    "hwidmatches": [
        "^DAMU.*",
        "^COZMO.*",
        "^WILLOW-TFIY .*",
        "^KENZO-IGRW.*",
        "^JUNIPER-HVPU .*|^JUNIPER-ZZCR .*",
        "^PICO-EXEM.*",
        "^ESCHE-.*",
        "^KAPPA-YFVF .*",
        "^KAPPA-EWFK .*",
        "^BURNET-.*",
        "^FENNEL14-.*",
        "^FENNEL-.*",
        "^MAKOMO-UTTX .*",
        "^DAMU.*",
        "^COZMO.*",
        "^WILLOW-TFIY .*",
        "^KENZO-IGRW.*",
        "^JUNIPER-HVPU .*|^JUNIPER-ZZCR .*",
        "^PICO-EXEM.*",
        "^ESCHE-.*",
        "^KAPPA-YFVF .*",
        "^KAPPA-EWFK .*",
        "^BURNET-.*",
        "^FENNEL14-.*",
        "^FENNEL-.*",
        "^MAKOMO-UTTX .*",
        "^DAMU.*",
        "^COZMO.*",
        "^WILLOW-TFIY .*",
        "^KENZO-IGRW.*",
        "^JUNIPER-HVPU .*|^JUNIPER-ZZCR .*",
        "^PICO-EXEM.*",
        "^ESCHE-.*",
        "^KAPPA-YFVF .*",
        "^KAPPA-EWFK .*",
        "^BURNET-.*",
        "^FENNEL14-.*",
        "^FENNEL-.*",
        "^MAKOMO-UTTX .*",
        "^DAMU.*",
        "^COZMO.*",
        "^WILLOW-TFIY .*",
        "^KENZO-IGRW.*",
        "^JUNIPER-HVPU .*|^JUNIPER-ZZCR .*",
        "^PICO-EXEM.*",
        "^ESCHE-.*",
        "^KAPPA-YFVF .*",
        "^KAPPA-EWFK .*",
        "^BURNET-.*",
        "^FENNEL14-.*",
        "^FENNEL-.*",
        "^MAKOMO-UTTX .*"
    ],
    "image_name": "jacuzzi",
    "manufacturers": [
        "Asus",
        "Acer",
        "Acer",
        "Acer",
        "Acer",
        "Acer",
        "HP",
        "HP",
        "HP",
        "HP",
        "Lenovo",
        "Lenovo",
        "Lenovo",
        "Asus",
        "Acer",
        "Acer",
        "Acer",
        "Acer",
        "Acer",
        "HP",
        "HP",
        "HP",
        "HP",
        "Lenovo",
        "Lenovo",
        "Lenovo",
        "Asus",
        "Acer",
        "Acer",
        "Acer",
        "Acer",
        "Acer",
        "HP",
        "HP",
        "HP",
        "HP",
        "Lenovo",
        "Lenovo",
        "Lenovo",
        "Asus",
        "Acer",
        "Acer",
        "Acer",
        "Acer",
        "Acer",
        "HP",
        "HP",
        "HP",
        "HP",
        "Lenovo",
        "Lenovo",
        "Lenovo"
    ],
    "md5": "7ad96e0827ef06ede76e7c9c1e4f737e",
    "models": [
        "ASUS Chromebook Flip CM3200FVA",
        "Acer Chromebook  314 (CB314-2H/CB314-2HT)",
        "Acer Chromebook 311 (C722/C722T)",
        "Acer Chromebook 311 (CB311-11H/CB311-11HT)",
        "Acer Chromebook Spin 311 (CP311-3H)",
        "Acer Chromebook Spin 311 - R722T",
        "HP Chromebook 11MK G9 EE",
        "HP Chromebook 11a na0",
        "HP Chromebook 11a-ne0",
        "HP Chromebook x360 11MK G3 EE",
        "Lenovo IdeaPad 3 Chromebook",
        "Lenovo IdeaPad Flex 3 Chromebook",
        "Lenovo 100e Gen 2",
        "ASUS Chromebook Flip CM3200FVA",
        "Acer Chromebook  314 (CB314-2H/CB314-2HT)",
        "Acer Chromebook 311 (C722/C722T)",
        "Acer Chromebook 311 (CB311-11H/CB311-11HT)",
        "Acer Chromebook Spin 311 (CP311-3H)",
        "Acer Chromebook Spin 311 - R722T",
        "HP Chromebook 11MK G9 EE",
        "HP Chromebook 11a na0",
        "HP Chromebook 11a-ne0",
        "HP Chromebook x360 11MK G3 EE",
        "Lenovo IdeaPad 3 Chromebook",
        "Lenovo IdeaPad Flex 3 Chromebook",
        "Lenovo 100e Gen 2",
        "ASUS Chromebook Flip CM3200FVA",
        "Acer Chromebook  314 (CB314-2H/CB314-2HT)",
        "Acer Chromebook 311 (C722/C722T)",
        "Acer Chromebook 311 (CB311-11H/CB311-11HT)",
        "Acer Chromebook Spin 311 (CP311-3H)",
        "Acer Chromebook Spin 311 - R722T",
        "HP Chromebook 11MK G9 EE",
        "HP Chromebook 11a na0",
        "HP Chromebook 11a-ne0",
        "HP Chromebook x360 11MK G3 EE",
        "Lenovo IdeaPad 3 Chromebook",
        "Lenovo IdeaPad Flex 3 Chromebook",
        "Lenovo 100e Gen 2",
        "ASUS Chromebook Flip CM3200FVA",
        "Acer Chromebook  314 (CB314-2H/CB314-2HT)",
        "Acer Chromebook 311 (C722/C722T)",
        "Acer Chromebook 311 (CB311-11H/CB311-11HT)",
        "Acer Chromebook Spin 311 (CP311-3H)",
        "Acer Chromebook Spin 311 - R722T",
        "HP Chromebook 11MK G9 EE",
        "HP Chromebook 11a na0",
        "HP Chromebook 11a-ne0",
        "HP Chromebook x360 11MK G3 EE",
        "Lenovo IdeaPad 3 Chromebook",
        "Lenovo IdeaPad Flex 3 Chromebook",
        "Lenovo 100e Gen 2"
    ],
    "names": [
        "ASUS Chromebook Flip CM3200FVA",
        "Acer Chromebook  314 (CB314-2H/CB314-2HT)",
        "Acer Chromebook 311 (C722/C722T)",
        "Acer Chromebook 311 (CB311-11H/CB311-11HT)",
        "Acer Chromebook Spin 311 (CP311-3H)",
        "Acer Chromebook Spin 311 - R722T",
        "HP Chromebook 11MK G9 EE",
        "HP Chromebook 11a na0",
        "HP Chromebook 11a-ne0",
        "HP Chromebook x360 11MK G3 EE",
        "IdeaPad 3 Chromebook",
        "IdeaPad Flex 3 Chromebook",
        "Lenovo 100e Gen 2",
        "ASUS Chromebook Flip CM3200FVA",
        "Acer Chromebook  314 (CB314-2H/CB314-2HT)",
        "Acer Chromebook 311 (C722/C722T)",
        "Acer Chromebook 311 (CB311-11H/CB311-11HT)",
        "Acer Chromebook Spin 311 (CP311-3H)",
        "Acer Chromebook Spin 311 - R722T",
        "HP Chromebook 11MK G9 EE",
        "HP Chromebook 11a na0",
        "HP Chromebook 11a-ne0",
        "HP Chromebook x360 11MK G3 EE",
        "IdeaPad 3 Chromebook",
        "IdeaPad Flex 3 Chromebook",
        "Lenovo 100e Gen 2",
        "ASUS Chromebook Flip CM3200FVA",
        "Acer Chromebook  314 (CB314-2H/CB314-2HT)",
        "Acer Chromebook 311 (C722/C722T)",
        "Acer Chromebook 311 (CB311-11H/CB311-11HT)",
        "Acer Chromebook Spin 311 (CP311-3H)",
        "Acer Chromebook Spin 311 - R722T",
        "HP Chromebook 11MK G9 EE",
        "HP Chromebook 11a na0",
        "HP Chromebook 11a-ne0",
        "HP Chromebook x360 11MK G3 EE",
        "IdeaPad 3 Chromebook",
        "IdeaPad Flex 3 Chromebook",
        "Lenovo 100e Gen 2",
        "ASUS Chromebook Flip CM3200FVA",
        "Acer Chromebook  314 (CB314-2H/CB314-2HT)",
        "Acer Chromebook 311 (C722/C722T)",
        "Acer Chromebook 311 (CB311-11H/CB311-11HT)",
        "Acer Chromebook Spin 311 (CP311-3H)",
        "Acer Chromebook Spin 311 - R722T",
        "HP Chromebook 11MK G9 EE",
        "HP Chromebook 11a na0",
        "HP Chromebook 11a-ne0",
        "HP Chromebook x360 11MK G3 EE",
        "IdeaPad 3 Chromebook",
        "IdeaPad Flex 3 Chromebook",
        "Lenovo 100e Gen 2"
    ],
    "sha1": "ab21b852c585fd64937f3ec4d8ff0bcfa823f58c",
    "url": "https://dl.google.com/dl/edgedl/chromeos/recovery/chromeos_15474.84.0_jacuzzi_recovery_stable-channel_mp-v13.bin.zip",
    "version": "15474.84.0",
    "zipfilesize": 1438609207
}